setup.py
BBinomial_2020/Binomialdistribution.py
BBinomial_2020/Gaussiandistribution.py
BBinomial_2020/Generaldistribution.py
BBinomial_2020/__init__.py
BBinomial_2020.egg-info/PKG-INFO
BBinomial_2020.egg-info/SOURCES.txt
BBinomial_2020.egg-info/dependency_links.txt
BBinomial_2020.egg-info/not-zip-safe
BBinomial_2020.egg-info/top_level.txt