Metadata-Version: 1.0
Name: BBinomial-2020
Version: 0.1
Summary: Gaussian distribution and Binomial Distributions
Home-page: UNKNOWN
Author: Biswarup Burman
Author-email: myemail@workspace.com
License: UNKNOWN
Platform: UNKNOWN
